.appveyor.yml
.gitignore
.gitmodules
.travis.yml
CMakeLists.txt
LICENSE.md
MANIFEST.in
README.md
RELEASE-VERSION
git_version.py
setup.py
amgcl/amg.hpp
amgcl/clock.hpp
amgcl/make_block_solver.hpp
amgcl/make_solver.hpp
amgcl/profiler.hpp
amgcl/runtime.hpp
amgcl/util.hpp
amgcl/adapter/block_matrix.hpp
amgcl/adapter/complex.hpp
amgcl/adapter/crs_builder.hpp
amgcl/adapter/crs_tuple.hpp
amgcl/adapter/epetra.hpp
amgcl/adapter/ublas.hpp
amgcl/adapter/zero_copy.hpp
amgcl/backend/blaze.hpp
amgcl/backend/block_crs.hpp
amgcl/backend/builtin.hpp
amgcl/backend/cuda.hpp
amgcl/backend/eigen.hpp
amgcl/backend/hpx.hpp
amgcl/backend/interface.hpp
amgcl/backend/vexcl.hpp
amgcl/backend/vexcl_static_matrix.hpp
amgcl/backend/viennacl.hpp
amgcl/backend/detail/default_direct_solver.hpp
amgcl/backend/detail/matrix_ops.hpp
amgcl/coarsening/aggregation.hpp
amgcl/coarsening/plain_aggregates.hpp
amgcl/coarsening/pointwise_aggregates.hpp
amgcl/coarsening/ruge_stuben.hpp
amgcl/coarsening/smoothed_aggr_emin.hpp
amgcl/coarsening/smoothed_aggregation.hpp
amgcl/coarsening/tentative_prolongation.hpp
amgcl/coarsening/detail/galerkin.hpp
amgcl/coarsening/detail/scaled_galerkin.hpp
amgcl/detail/inverse.hpp
amgcl/detail/qr.hpp
amgcl/detail/sort_row.hpp
amgcl/detail/spgemm.hpp
amgcl/io/binary.hpp
amgcl/io/mm.hpp
amgcl/mpi/block_preconditioner.hpp
amgcl/mpi/direct_solver.hpp
amgcl/mpi/distributed_matrix.hpp
amgcl/mpi/inner_product.hpp
amgcl/mpi/make_solver.hpp
amgcl/mpi/pastix.hpp
amgcl/mpi/schur_pressure_correction.hpp
amgcl/mpi/skyline_lu.hpp
amgcl/mpi/subdomain_deflation.hpp
amgcl/mpi/util.hpp
amgcl/perf_counter/clock.hpp
amgcl/perf_counter/cray_energy.hpp
amgcl/perf_counter/mpi_aggregator.hpp
amgcl/preconditioner/cpr.hpp
amgcl/preconditioner/cpr_drs.hpp
amgcl/preconditioner/dummy.hpp
amgcl/preconditioner/runtime.hpp
amgcl/preconditioner/schur_pressure_correction.hpp
amgcl/relaxation/as_preconditioner.hpp
amgcl/relaxation/chebyshev.hpp
amgcl/relaxation/cusparse_ilu0.hpp
amgcl/relaxation/damped_jacobi.hpp
pyamgcl.egg-info/PKG-INFO
pyamgcl.egg-info/SOURCES.txt
pyamgcl.egg-info/dependency_links.txt
pyamgcl.egg-info/not-zip-safe
pyamgcl.egg-info/requires.txt
pyamgcl.egg-info/top_level.txt
