Metadata-Version: 1.0
Name: pyamgcl
Version: 1.0.0.post4
Summary: Solution of large sparse linear systems with Algebraic Multigrid Method
Home-page: https://github.com/ddemidov/amgcl
Author: Denis Demidov
Author-email: dennis.demidov@gmail.com
License: MIT
Platform: UNKNOWN
